LICENSE
MANIFEST.in
README.md
setup.py
inglass/__init__.py
inglass/config.yaml
inglass/inglass.py
inglass.egg-info/PKG-INFO
inglass.egg-info/SOURCES.txt
inglass.egg-info/dependency_links.txt
inglass.egg-info/entry_points.txt
inglass.egg-info/not-zip-safe
inglass.egg-info/requires.txt
inglass.egg-info/top_level.txt
inglass/logs/0/2014/5/1.csv
inglass/logs/0/2014/5/11.csv
inglass/logs/0/2014/5/14.csv
inglass/logs/0/2014/5/19.csv
inglass/logs/0/2014/5/8.csv
inglass/logs/1/2014/5/11.csv
inglass/logs/1/2014/5/14.csv
inglass/logs/1/2014/5/19.csv
inglass/static/.DS_Store
inglass/static/icomoon.svg
inglass/static/icomoon.woff
inglass/static/main.css
inglass/static/main.js
inglass/templates/about.html
inglass/templates/base.html
inglass/templates/current.html
inglass/templates/graph.html