Metadata-Version: 1.0
Name: inglass
Version: 0.1
Summary: A tool for monitoring and logging the temperature from a TEMPer USB Thermometer
Home-page: https://github.com/chrisknepper/in-glass
Author: Chris Knepper, Lance Laughlin, Dustin Raimondi
Author-email: chris82thekid@gmail.com
License: LICENSE
Keywords: temperature flask temper usb logging
Platform: UNKNOWN
